cordwainer-0.0.2.dist-info/DESCRIPTION.rst
cordwainer-0.0.2.dist-info/top_level.txt
cordwainer-0.0.2.dist-info/RECORD
cordwainer-0.0.2.dist-info/WHEEL
cordwainer-0.0.2.dist-info/metadata.json
cordwainer-0.0.2.dist-info/METADATA
cordwainer/__init__.py
cordwainer/csv.py
cordwainer/dicts.py
cordwainer/utils.py
tests/test_basics.py
tests/test_dicts.py
tests/__init__.py
