Metadata-Version: 2.0
Name: cordwainer
Version: 0.0.2
Summary: A better CSV module
Home-page: https://github.com/caktus/cordwainer
Author: Dan Poirier
Author-email: dpoirier@caktusgroup.com
License: APL2
Platform: UNKNOWN
Classifier: Development Status :: 3 - Alpha
Classifier: Intended Audience :: Developers
Classifier: License :: OSI Approved :: Apache Software License
Classifier: Operating System :: OS Independent
Classifier: Programming Language :: Python :: 2.7
Classifier: Programming Language :: Python :: 3
Classifier: Programming Language :: Python :: 3.3
Classifier: Programming Language :: Python :: 3.4
Classifier: Topic :: Software Development :: Libraries
Requires-Dist: six (>=1.7)
